kw/__init__.py
kw-0.0.5.dist-info/licenses/LICENSE
kw-0.0.5.dist-info/METADATA
kw-0.0.5.dist-info/WHEEL
kw-0.0.5.dist-info/top_level.txt
kw-0.0.5.dist-info/RECORD
