Metadata-Version: 2.4
Name: kw
Version: 0.0.5
Summary: Utils to work with storage
Home-page: https://github.com/t-c-w/kw
Author: Thor Whalen
License: apache-2.0
Platform: any
License-File: LICENSE
Dynamic: license-file
